aws_utils/__init__.py
aws_utils/exceptions.py
aws_utils/notifications.py
aws_utils/ssm.py
nw_aws_utils-1.0.7.dist-info/METADATA
nw_aws_utils-1.0.7.dist-info/WHEEL
nw_aws_utils-1.0.7.dist-info/top_level.txt
nw_aws_utils-1.0.7.dist-info/RECORD
