Metadata-Version: 2.1
Name: nw-aws-utils
Version: 1.0.7
Summary: Reusable components for interacting with AWS services
Home-page: http://github.com/marple-newsrobot/newsworthy-aws-utils
Author: Journalism Robotics Stockholm
Author-email: contact@newsworthy.se
License: MIT
Platform: UNKNOWN
Requires-Dist: boto3 (>=1.9)
